abe_plugin/__init__.py
abe_plugin/backends/__init__.py
abe_plugin/backends/message_queue/__init__.py
abe_plugin/backends/message_queue/service/__init__.py
abe_plugin/backends/message_queue/service/redis.py
abe_redis-0.1.0.dist-info/METADATA
abe_redis-0.1.0.dist-info/WHEEL
abe_redis-0.1.0.dist-info/entry_points.txt
abe_redis-0.1.0.dist-info/licenses/LICENSE
abe_redis-0.1.0.dist-info/RECORD
