Metadata-Version: 2.4
Name: abe-redis
Version: 0.1.0
Summary: 📮 A Redis-based abstracted backend (abe) for abstract backend message queue.
Project-URL: Homepage, https://github.com/Chisanan232/abe-redis
Project-URL: Repository, https://github.com/Chisanan232/abe-redis
Project-URL: Documentation, https://chisanan232.github.io/abe-redis/
Project-URL: Changelog, https://chisanan232.github.io/abe-redis/docs/next/changelog
Project-URL: Project Management, https://app.clickup.com/9018752317/v/f/90185744047/90184991515
Author-email: Chisanan232 <chi10211201@cycu.org.tw>
License: 
License-File: LICENSE
Keywords: backend,implement-layer,implementation,message-queue,queue
Classifier: Development Status :: 3 - Alpha
Classifier: Intended Audience :: Developers
Classifier: License :: OSI Approved :: MIT License
Classifier: Operating System :: OS Independent
Classifier: Programming Language :: Python :: 3
Classifier: Programming Language :: Python :: 3.12
Classifier: Programming Language :: Python :: 3.13
Classifier: Topic :: Software Development :: Libraries :: Python Modules
Classifier: Topic :: Utilities
Requires-Python: <3.14,>=3.12
Requires-Dist: abstract-backend>=0.0.1
Requires-Dist: redis[hiredis]>=6.4.0
